Metadata-Version: 2.1
Name: up-pypi-exo
Version: 0.1
Summary: Gaussian distributions
